django_docusign/.__init__.py.un~
django_docusign/.api.py.un~
django_docusign/.backend.py.un~
django_docusign/.views.py.un~
django_docusign/__init__.py
django_docusign/api.py
django_docusign/backend.py
django_docusign/forms.py
django_docusign/views.py
django_docusign-3.3.dist-info/AUTHORS
django_docusign-3.3.dist-info/LICENSE
django_docusign-3.3.dist-info/METADATA
django_docusign-3.3.dist-info/WHEEL
django_docusign-3.3.dist-info/top_level.txt
django_docusign-3.3.dist-info/RECORD
