Metadata-Version: 2.1
Name: django-docusign
Version: 3.3
Summary: Django application for DocuSign signature SAAS platform.
Home-page: https://django-docusign.readthedocs.io/
Author: Benoît Bryon
Author-email: novafloss@people-doc.com
License: BSD
Keywords: d,o,c,u,s,i,g,n, ,s,i,g,n,a,t,u,r,e, ,b,a,c,k,e,n,d, ,p,y,d,o,c,u,s,i,g,n, ,d,j,a,n,g,o,-,a,n,y,s,i,g,n
Platform: UNKNOWN
Classifier: Development Status :: 5 - Production/Stable
Classifier: License :: OSI Approved :: BSD License
Classifier: Programming Language :: Python :: 2
Classifier: Programming Language :: Python :: 2.7
Classifier: Programming Language :: Python :: 3
Classifier: Programming Language :: Python :: 3.4
Classifier: Programming Language :: Python :: 3.5
Classifier: Programming Language :: Python :: 3.6
Classifier: Programming Language :: Python :: 3.7
Classifier: Framework :: Django
Classifier: Framework :: Django :: 1.8
Classifier: Framework :: Django :: 1.9
Classifier: Framework :: Django :: 1.10
Classifier: Framework :: Django :: 1.11
Classifier: Framework :: Django :: 2.0
Classifier: Framework :: Django :: 2.1
Requires-Dist: Django (>=1.8)
Requires-Dist: django-anysign (<2.0,>=1.2)
Requires-Dist: pydocusign (<3.0,>=2.2)
Requires-Dist: setuptools
Provides-Extra: test
Requires-Dist: tox ; extra == 'test'
Requires-Dist: mock ; extra == 'test'
